{
  "title": "Magnets",
  "slug": "magnets",
  "label": "Magnet",
  "order": 1,
  "home_label": "Magnets",
  "section_copy": "Prague and Czech-theme magnets arranged for souvenir retail, museum shops, and visitor stores that want gift-ready designs instead of generic tourist clutter.",
  "page_intro": "A flexible magnet range for Prague and Czech souvenir merchandising. Suitable for low-MOQ testing, mixed display racks, and category expansion after initial sell-through.",
  "buyer_fit": [
    "Souvenir shops",
    "Museum shops",
    "Visitor stores",
    "City-gift counters"
  ],
  "default_note": "Suitable for souvenir shops, museum shops, visitor stores, and low-MOQ product testing.",
  "products": [
    {
      "name": "Prague Tram Collage Magnet",
      "image": "assets/magnets_01.jpg",
      "alt": "Prague Tram Collage Magnet",
      "note": "Good for counter displays and low-MOQ souvenir testing.",
      "badge": "Magnet"
    },
    {
      "name": "I Love Prague Tram Magnet",
      "image": "assets/magnets_02.jpg",
      "alt": "I Love Prague Tram Magnet",
      "note": "A clear Prague-theme seller for tourist impulse purchase zones.",
      "badge": "Magnet"
    },
    {
      "name": "Bridge & Skyline Magnet",
      "image": "assets/magnets_03.jpg",
      "alt": "Bridge & Skyline Magnet",
      "note": "Works well in classic landmark-focused souvenir assortments.",
      "badge": "Magnet"
    },
    {
      "name": "Prague Clock Monument Magnet",
      "image": "assets/magnets_04.jpg",
      "alt": "Prague Clock Monument Magnet",
      "note": "Suitable for museum and monument-led gift displays.",
      "badge": "Magnet"
    },
    {
      "name": "Prague Beer Stein Magnet",
      "image": "assets/magnets_05.jpg",
      "alt": "Prague Beer Stein Magnet",
      "note": "Fits beer, Prague, and city-gift themed mixed displays.",
      "badge": "Magnet"
    },
    {
      "name": "Prague Skyline Fan Magnet",
      "image": "assets/magnets_06.jpg",
      "alt": "Prague Skyline Fan Magnet",
      "note": "A broader city-theme option for compact shelf sets.",
      "badge": "Magnet"
    },
    {
      "name": "Prague Barrel Magnet",
      "image": "assets/magnets_07.jpg",
      "alt": "Prague Barrel Magnet",
      "note": "Useful for rustic souvenir corners and mixed tourist assortments.",
      "badge": "Magnet"
    },
    {
      "name": "Czech Republic Clock Magnet",
      "image": "assets/magnets_08.jpg",
      "alt": "Czech Republic Clock Magnet",
      "note": "A Czech-wide story piece beyond Prague-only selections.",
      "badge": "Magnet"
    },
    {
      "name": "Black Prague Clock Magnet",
      "image": "assets/magnets_09.jpg",
      "alt": "Black Prague Clock Magnet",
      "note": "A darker premium-style option for more curated racks.",
      "badge": "Magnet"
    },
    {
      "name": "Prague Gear Clock Magnet",
      "image": "assets/magnets_10.jpg",
      "alt": "Prague Gear Clock Magnet",
      "note": "Adds mechanical detail and visual variation to a display wall.",
      "badge": "Magnet"
    },
    {
      "name": "I Love Prague Artisan Magnet",
      "image": "assets/magnets_11.jpg",
      "alt": "I Love Prague Artisan Magnet",
      "note": "A gift-ready Prague message piece for fast tourist recognition.",
      "badge": "Magnet"
    },
    {
      "name": "Prague Folk Figure Magnet",
      "image": "assets/magnets_12.jpg",
      "alt": "Prague Folk Figure Magnet",
      "note": "Useful for adding local character motifs into the assortment.",
      "badge": "Magnet"
    },
    {
      "name": "Prague Castle Scenic Magnet",
      "image": "assets/magnets_13.jpg",
      "alt": "Prague Castle Scenic Magnet",
      "note": "A landmark-led product suited to traditional Prague gift channels.",
      "badge": "Magnet"
    },
    {
      "name": "Folk Couple Panorama Magnet",
      "image": "assets/magnets_14.jpg",
      "alt": "Folk Couple Panorama Magnet",
      "note": "Helps widen the range with folk-style souvenir storytelling.",
      "badge": "Magnet"
    },
    {
      "name": "Charles Bridge Embrace Magnet",
      "image": "assets/magnets_15.jpg",
      "alt": "Charles Bridge Embrace Magnet",
      "note": "Ideal for romantic Prague icon merchandising.",
      "badge": "Magnet"
    },
    {
      "name": "Round Prague Panorama Magnet",
      "image": "assets/magnets_16.jpg",
      "alt": "Round Prague Panorama Magnet",
      "note": "A compact city-view format for mixed magnet stands.",
      "badge": "Magnet"
    },
    {
      "name": "Historic Czech Republic Magnet",
      "image": "assets/magnets_17.jpg",
      "alt": "Historic Czech Republic Magnet",
      "note": "Useful when a store wants a broader Czech souvenir mix.",
      "badge": "Magnet"
    },
    {
      "name": "Prague Astronomical Clock Magnet",
      "image": "assets/magnets_18.jpg",
      "alt": "Prague Astronomical Clock Magnet",
      "note": "A strong heritage motif for landmark-driven sales points.",
      "badge": "Magnet"
    },
    {
      "name": "Prague Heritage Panorama Magnet",
      "image": "assets/magnets_19.jpg",
      "alt": "Prague Heritage Panorama Magnet",
      "note": "Adds scenic breadth to Prague city-gift assortments.",
      "badge": "Magnet"
    },
    {
      "name": "Beer Mug Souvenir Magnet",
      "image": "assets/magnets_20.jpg",
      "alt": "Beer Mug Souvenir Magnet",
      "note": "A practical filler SKU for beer-themed souvenir displays.",
      "badge": "Magnet"
    }
  ]
}